eta_ctrl/__init__.py
eta_ctrl/agents/__init__.py
eta_ctrl/agents/math_solver.py
eta_ctrl/agents/nsga2.py
eta_ctrl/agents/rule_based.py
eta_ctrl/common/__init__.py
eta_ctrl/common/callbacks.py
eta_ctrl/common/common.py
eta_ctrl/common/extractors.py
eta_ctrl/common/policies.py
eta_ctrl/common/processors.py
eta_ctrl/common/schedules.py
eta_ctrl/config/__init__.py
eta_ctrl/config/config.py
eta_ctrl/config/config_run.py
eta_ctrl/config/config_settings.py
eta_ctrl/config/config_setup.py
eta_ctrl/core.py
eta_ctrl/envs/__init__.py
eta_ctrl/envs/base_env.py
eta_ctrl/envs/julia_env.py
eta_ctrl/envs/live_env.py
eta_ctrl/envs/no_vec_env.py
eta_ctrl/envs/pyomo_env.py
eta_ctrl/envs/sim_env.py
eta_ctrl/envs/state.py
eta_ctrl/ju_extensions/.JuliaFormatter.toml
eta_ctrl/ju_extensions/Manifest.toml
eta_ctrl/ju_extensions/Project.toml
eta_ctrl/ju_extensions/src/agents/NSGA2.jl
eta_ctrl/ju_extensions/src/ju_extensions.jl
eta_ctrl/ju_extensions/src/utils.jl
eta_ctrl/ju_extensions/test/agents/NSGA2.jl
eta_ctrl/ju_extensions/test/runtests.jl
eta_ctrl/py.typed
eta_ctrl/simulators/__init__.py
eta_ctrl/simulators/fmu.py
eta_ctrl/timeseries/__init__.py
eta_ctrl/timeseries/dataframes.py
eta_ctrl/timeseries/scenarios.py
eta_ctrl/util/__init__.py
eta_ctrl/util/io_utils.py
eta_ctrl/util/julia_utils.py
eta_ctrl/util/logging_utils.py
eta_ctrl/util/type_annotations.py
eta_ctrl/util/utils.py
examples/__init__.py
examples/damped_oscillator/__init__.py
examples/damped_oscillator/config_conventional.json
examples/damped_oscillator/config_learning.json
examples/damped_oscillator/controller.py
examples/damped_oscillator/damped_oscillator.fmu
examples/damped_oscillator/damped_oscillator.py
examples/damped_oscillator/main.py
examples/pendulum/__init__.py
examples/pendulum/assets/clockwise.png
examples/pendulum/config_conventional.json
examples/pendulum/config_learning.json
examples/pendulum/controller.py
examples/pendulum/main.py
examples/pendulum/pendulum.py
eta_ctrl-0.1.0.dist-info/AUTHORS.rst
eta_ctrl-0.1.0.dist-info/LICENSE
eta_ctrl-0.1.0.dist-info/METADATA
eta_ctrl-0.1.0.dist-info/WHEEL
eta_ctrl-0.1.0.dist-info/entry_points.txt
eta_ctrl-0.1.0.dist-info/RECORD
