Metadata-Version: 2.3
Name: eta-ctrl
Version: 0.1.0
Summary: A framework for researching energy optimization of factory operations.
License: BSD-2-Clause
Keywords: rolling horizon optimization,simulators,industrial energy optimization
Author: Technical University of Darmstadt, Institute for Production Management, Technology and Machine Tools (PTW)
Author-email: info@ptw.tu-darmstadt.de
Maintainer: Andreas Clement
Maintainer-email: A.Clement@PTW.TU-Darmstadt.de
Requires-Python: >=3.10.16,<3.13
Classifier: Development Status :: 4 - Beta
Classifier: Intended Audience :: Developers
Classifier: Intended Audience :: Education
Classifier: Intended Audience :: Manufacturing
Classifier: Intended Audience :: Science/Research
Classifier: License :: OSI Approved :: BSD License
Classifier: Operating System :: OS Independent
Classifier: Programming Language :: Python :: 3
Classifier: Programming Language :: Python :: 3.11
Classifier: Programming Language :: Python :: 3.12
Classifier: Topic :: Scientific/Engineering :: Artificial Intelligence
Classifier: Topic :: Software Development :: Libraries :: Python Modules
Provides-Extra: docs
Provides-Extra: examples
Requires-Dist: attrs (>=25.3.0,<26.0.0)
Requires-Dist: eta-nexus (>=0.0.1,<0.1.0)
Requires-Dist: fmpy (>=0.3.5,<0.4.0)
Requires-Dist: gymnasium (==1.0.0)
Requires-Dist: julia (>=0.6.2,<0.7.0)
Requires-Dist: keyboard (>=0.13.5,<0.14.0) ; extra == "examples"
Requires-Dist: matplotlib (>=3.9.2,<3.10.0) ; extra == "examples"
Requires-Dist: numpy (>=2.0.0,<3.0.0)
Requires-Dist: onnxruntime (==1.21.0) ; extra == "examples"
Requires-Dist: pandas (>=2.2.2,<2.3.0)
Requires-Dist: pygame (>=2.5.2,<2.6.0) ; extra == "examples"
Requires-Dist: pyglet (<2.0.0) ; extra == "examples"
Requires-Dist: pyomo (>=6.9.2,<6.10.0)
Requires-Dist: python-dateutil (>=2.8.2,<3.0.0)
Requires-Dist: pyyaml (>=6.0.2,<7.0.0)
Requires-Dist: sphinx (>=7.1.2,<8.0.0) ; extra == "docs"
Requires-Dist: sphinx-copybutton (>=0.5.2,<1.0.0) ; extra == "docs"
Requires-Dist: sphinx-rtd-theme (>=1.3.0,<2.0.0) ; extra == "docs"
Requires-Dist: stable-baselines3 (>=2.4.0,<3.0.0)
Requires-Dist: tensorboard (>=2.14.0,<2.15.0)
Requires-Dist: toml (>=0.10.2,<0.11.0)
Requires-Dist: torch (>=2.4.0,<2.5.0)
Project-URL: Documentation, https://eta-ctrl.readthedocs.io/
Project-URL: Homepage, https://www.ptw.tu-darmstadt.de
Project-URL: Issues, https://git.ptw.maschinenbau.tu-darmstadt.de/eta-fabrik/public/eta-ctrl/-/issues
Project-URL: Repository, https://github.com/PTW-TUDa/eta_ctrl/
